tallyerp/__init__.py
tallyerp/config.py
tallyerp/entities/__init__.py
tallyerp/entities/api/__init__.py
tallyerp/entities/api/request/__init__.py
tallyerp/entities/api/request/masterImport.py
tallyerp/entities/api/response/__init__.py
tallyerp/entities/api/response/common.py
tallyerp/entities/api/response/masterImport.py
tallyerp/entities/masters/__init__.py
tallyerp/entities/masters/group.py
tallyerp/entities/masters/ledger.py
tallyerp/gateways/__init__.py
tallyerp/gateways/master.py
tallyerp/gateways/tally.py
tallyerp/providers/TallyApi.py
tallyerp/providers/TallyRequest.py
tallyerp/providers/TallyResponse.py
tallyerp/providers/__init__.py
tallyerp/repositories/__init__.py
tallyerp/repositories/masters/Group.py
tallyerp/repositories/masters/IBase.py
tallyerp/repositories/masters/Ledger.py
tallyerp/repositories/masters/__init__.py
tallyerp/usecases/__init__.py
tallyerp/usecases/master/__init__.py
tallyerp/usecases/master/group/__init__.py
tallyerp/usecases/master/group/createGroup/__init__.py
tallyerp/usecases/master/group/createGroup/dto.py
tallyerp/usecases/master/group/createGroup/useCase.py
tallyerp/usecases/master/ledger/__init__.py
tallyerp/usecases/master/ledger/createLedger/__init__.py
tallyerp/usecases/master/ledger/createLedger/dto.py
tallyerp/usecases/master/ledger/createLedger/useCase.py
tallyerp-0.0.13.dist-info/METADATA
tallyerp-0.0.13.dist-info/WHEEL
tallyerp-0.0.13.dist-info/top_level.txt
tallyerp-0.0.13.dist-info/RECORD
