Metadata-Version: 2.1
Name: tallyerp
Version: 0.0.13
Summary: Tally ERP python
Home-page: https://citrisys.com
Author: citrisys
Author-email: dev@citrisys.com
Requires: requests
Requires: loguru
Requires: xsdata
